eWarrant/__init__.py
eWarrant/eWarrant.py
ewarrant-0.0.9.dist-info/LICENSE
ewarrant-0.0.9.dist-info/METADATA
ewarrant-0.0.9.dist-info/WHEEL
ewarrant-0.0.9.dist-info/top_level.txt
ewarrant-0.0.9.dist-info/RECORD
